ape_farcaster/__init__.py
ape_farcaster/client.py
ape_farcaster/config.py
ape_farcaster/models.py
ape_farcaster/py.typed
ape_farcaster/utils/__init__.py
ape_farcaster/utils/stream_generator.py
ape_farcaster-0.8.0b0.dist-info/LICENSE
ape_farcaster-0.8.0b0.dist-info/METADATA
ape_farcaster-0.8.0b0.dist-info/WHEEL
ape_farcaster-0.8.0b0.dist-info/top_level.txt
ape_farcaster-0.8.0b0.dist-info/RECORD
