Metadata-Version: 2.1
Name: ape-farcaster
Version: 0.8.0b0
Summary: ape-farcaster is a Python SDK for the Farcaster Protocol
Author-email: Andreessen Horowitz <crypto-engineering@a16z.com>, "ApeWorX LTD." <admin@apeworx.io>
Maintainer-email: "ApeWorX LTD." <admin@apeworx.io>
Project-URL: Repository, https://github.com/ApeWorX/ape-farcaster
Project-URL: Homepage, https://github.com/ApeWorX/ape-farcaster/
Classifier: Development Status :: 3 - Alpha
Classifier: Intended Audience :: Developers
Classifier: Operating System :: OS Independent
Classifier: Topic :: Software Development :: Libraries :: Python Modules
Classifier: License :: OSI Approved :: MIT License
Classifier: Programming Language :: Python :: 3
Classifier: Programming Language :: Python :: 3.8
Classifier: Programming Language :: Python :: 3.9
Classifier: Programming Language :: Python :: 3.10
Classifier: Programming Language :: Python :: 3.11
Requires-Python: <4,>=3.10
License-File: LICENSE
Requires-Dist: eth-ape >=0.8
Requires-Dist: python-dotenv <1.1,>=0.21
Requires-Dist: pydantic <3,>=2.6.4
Requires-Dist: pyhumps >=3.7.2
Requires-Dist: requests >=2.28.1
Requires-Dist: canonicaljson <3.0.0,>=1.6.4
Requires-Dist: eth-account
Requires-Dist: parsimonious <0.11.0,>=0.10.0
Provides-Extra: dev
Requires-Dist: IPython ; extra == 'dev'
Requires-Dist: ape-farcaster[docs,lint,release,test] ; extra == 'dev'
Requires-Dist: pyupgrade >=3.3.1 ; extra == 'dev'
Requires-Dist: pre-commit <4.0,>=2.15 ; extra == 'dev'
Provides-Extra: docs
Requires-Dist: docconvert >=2.0.0 ; extra == 'docs'
Requires-Dist: mkdocs >=1.4.2 ; extra == 'docs'
Requires-Dist: mkdocs-material >=9.0.5 ; extra == 'docs'
Requires-Dist: mkdocstrings <0.24.0,>=0.19.1 ; extra == 'docs'
Requires-Dist: mkdocstrings-python <0.11.0,>=0.8.3 ; extra == 'docs'
Requires-Dist: cairosvg >=2.6.0 ; extra == 'docs'
Provides-Extra: lint
Requires-Dist: black ; extra == 'lint'
Requires-Dist: isort[colors] ; extra == 'lint'
Requires-Dist: mypy >=1.0 ; extra == 'lint'
Requires-Dist: mypy-extensions >=1.0.0 ; extra == 'lint'
Requires-Dist: pydocstyle >=6.3.0 ; extra == 'lint'
Requires-Dist: pylint >=2.11.1 ; extra == 'lint'
Requires-Dist: darglint >=1.8.1 ; extra == 'lint'
Requires-Dist: types-requests >=2.31.0.2 ; extra == 'lint'
Requires-Dist: bandit >=1.7.1 ; extra == 'lint'
Provides-Extra: release
Requires-Dist: setuptools-scm ; extra == 'release'
Requires-Dist: wheel ; extra == 'release'
Provides-Extra: test
Requires-Dist: pytest >=7.2.1 ; extra == 'test'
Requires-Dist: coverage >=7.2.1 ; extra == 'test'
Requires-Dist: coverage-badge >=1.1.0 ; extra == 'test'
Requires-Dist: pytest-dependency >=0.5.1 ; extra == 'test'
Requires-Dist: pytest-html >=3.1.1 ; extra == 'test'
Requires-Dist: pytest-cov >=4.0.0 ; extra == 'test'
Requires-Dist: pytest-recording >=0.12.1 ; extra == 'test'
Requires-Dist: vcrpy >=5.1.0 ; extra == 'test'
